dbbackup/__init__.py
dbbackup/apps.py
dbbackup/checks.py
dbbackup/log.py
dbbackup/settings.py
dbbackup/storage.py
dbbackup/utils.py
dbbackup/db/__init__.py
dbbackup/db/base.py
dbbackup/db/exceptions.py
dbbackup/db/mongodb.py
dbbackup/db/mysql.py
dbbackup/db/postgresql.py
dbbackup/db/sqlite.py
dbbackup/management/__init__.py
dbbackup/management/commands/__init__.py
dbbackup/management/commands/_base.py
dbbackup/management/commands/dbbackup.py
dbbackup/management/commands/dbrestore.py
dbbackup/management/commands/listbackups.py
dbbackup/management/commands/mediabackup.py
dbbackup/management/commands/mediarestore.py
dbbackup/tests/__init__.py
dbbackup/tests/settings.py
dbbackup/tests/test_checks.py
dbbackup/tests/test_log.py
dbbackup/tests/test_storage.py
dbbackup/tests/test_utils.py
dbbackup/tests/utils.py
dbbackup/tests/commands/__init__.py
dbbackup/tests/commands/test_base.py
dbbackup/tests/commands/test_dbbackup.py
dbbackup/tests/commands/test_dbrestore.py
dbbackup/tests/commands/test_listbackups.py
dbbackup/tests/commands/test_mediabackup.py
dbbackup/tests/functional/__init__.py
dbbackup/tests/functional/test_commands.py
dbbackup/tests/test_connectors/__init__.py
dbbackup/tests/test_connectors/test_base.py
dbbackup/tests/test_connectors/test_mongodb.py
dbbackup/tests/test_connectors/test_mysql.py
dbbackup/tests/test_connectors/test_postgresql.py
dbbackup/tests/test_connectors/test_sqlite.py
dbbackup/tests/testapp/__init__.py
dbbackup/tests/testapp/models.py
dbbackup/tests/testapp/urls.py
dbbackup/tests/testapp/views.py
dbbackup/tests/testapp/management/__init__.py
dbbackup/tests/testapp/management/commands/__init__.py
dbbackup/tests/testapp/management/commands/count.py
dbbackup/tests/testapp/management/commands/feed.py
dbbackup/tests/testapp/migrations/0001_initial.py
dbbackup/tests/testapp/migrations/__init__.py
nova_django_dbbackup-3.2.2.dist-info/AUTHORS.txt
nova_django_dbbackup-3.2.2.dist-info/LICENSE.txt
nova_django_dbbackup-3.2.2.dist-info/METADATA
nova_django_dbbackup-3.2.2.dist-info/WHEEL
nova_django_dbbackup-3.2.2.dist-info/top_level.txt
nova_django_dbbackup-3.2.2.dist-info/RECORD
