Metadata-Version: 2.1
Name: nova-django-dbbackup
Version: 3.2.2
Summary: Management commands to help backup and restore a project database and media
Home-page: https://github.com/letsnova/django-dbbackup
Author: Michael Shepanski
Author-email: mjs7231@gmail.com
License: BSD
Keywords: django,database,media,backup,amazon,s3dropbox
Platform: UNKNOWN
Classifier: Development Status :: 4 - Beta
Classifier: Environment :: Web Environment
Classifier: Environment :: Console
Classifier: Framework :: Django
Classifier: Intended Audience :: Developers
Classifier: Intended Audience :: System Administrators
Classifier: License :: OSI Approved :: BSD License
Classifier: Natural Language :: English
Classifier: Operating System :: OS Independent
Classifier: Programming Language :: Python
Classifier: Programming Language :: Python :: 2
Classifier: Programming Language :: Python :: 2.7
Classifier: Programming Language :: Python :: 3
Classifier: Programming Language :: Python :: 3.2
Classifier: Programming Language :: Python :: 3.3
Classifier: Programming Language :: Python :: 3.4
Classifier: Programming Language :: Python :: 3.5
Classifier: Topic :: Database
Classifier: Topic :: System :: Archiving
Classifier: Topic :: System :: Archiving :: Backup
Classifier: Topic :: System :: Archiving :: Compression
Requires-Dist: pytz
Requires-Dist: six
Requires-Dist: Django (>=1.5)
